[
    {
        "photoURL": "https://a0.muscache.com/im/pictures/user/f7bbd9be-8cae-49bb-8e3f-f8c5ea08292c.jpg?im_w=240",
        "name": "Namrita",
        "date": "December 2021",
        "review": "Great place to stay, easy check in & check out with host, kitchen was very well stocked and place was very clean and cozy!"
    },
    {
        "photoURL": "https://a0.muscache.com/im/pictures/user/f8b75502-785c-4707-b7a4-02d6f9025532.jpg?im_w=240",
        "name": "Kimiye",
        "date": "November 2021",
        "review": "Beautiful stay. My grandparents stayed in this suite for their week long vacation. They really loved it. Super clean, with everything you would need and more. Antonio gave them his phone number in case which is wonderful. Thank you!!"
    },
    {
        "photoURL": "https://a0.muscache.com/im/pictures/user/b9845771-5e30-482d-9b63-31cbe102a98c.jpg?im_w=240",
        "name": "Kawssar",
        "date": "September 2021",
        "review": "Great place, very well located only a few minutes away from a bus stop"
    },
    {
        "photoURL": "https://a0.muscache.com/im/pictures/user/10c0ca89-51e0-463d-8eda-0a95183b2052.jpg?im_w=240",
        "name": "Marilyn",
        "date": "July 2021",
        "review": "This place was amazing, clean and in a great location! Would definitely recommend staying here!"
    },
    {
        "photoURL": "https://a0.muscache.com/im/pictures/user/cf1d03f3-56a2-4dd1-a621-0c3bca9e811c.jpg?im_w=240",
        "name": "Abed",
        "date": "June 2021",
        "review": "Antonio and Lilly are fantastic hosts - so friendly and welcoming. We felt right at home staying there, and the suite is very nice and well equipped with its modern finishings. A wonderful stay!"
    },
]